{
  "filename": "circuit_015.png",
  "folder": "train",
  "num_gates": 11,
  "gates": [
    {
      "id": "g0",
      "type": "NOR",
      "x": 0,
      "y": 0,
      "inputs": 2
    },
    {
      "id": "g1",
      "type": "NAND",
      "x": 2,
      "y": 0,
      "inputs": 2
    },
    {
      "id": "g2",
      "type": "NOT",
      "x": 4,
      "y": 0,
      "inputs": 1
    },
    {
      "id": "g3",
      "type": "OR",
      "x": 6,
      "y": 0,
      "inputs": 2
    },
    {
      "id": "g4",
      "type": "OR",
      "x": 8,
      "y": 0,
      "inputs": 2
    },
    {
      "id": "g5",
      "type": "NOR",
      "x": 10,
      "y": 0,
      "inputs": 2
    },
    {
      "id": "g6",
      "type": "NAND",
      "x": 12,
      "y": 0,
      "inputs": 2
    },
    {
      "id": "g7",
      "type": "AND",
      "x": 14,
      "y": 0,
      "inputs": 2
    },
    {
      "id": "g8",
      "type": "AND",
      "x": 16,
      "y": 0,
      "inputs": 2
    },
    {
      "id": "g9",
      "type": "AND",
      "x": 18,
      "y": 0,
      "inputs": 2
    },
    {
      "id": "g10",
      "type": "OR",
      "x": 20,
      "y": 0,
      "inputs": 2
    }
  ]
}